renzmc/__init__.py
renzmc/__main__.py
renzmc/repl.py
renzmc/version.py
renzmc/builtins/__init__.py
renzmc/builtins/dict_functions/__init__.py
renzmc/builtins/iteration_functions/__init__.py
renzmc/builtins/list_functions/__init__.py
renzmc/builtins/python_integration/__init__.py
renzmc/builtins/string_functions/__init__.py
renzmc/builtins/system_functions/__init__.py
renzmc/builtins/type_functions/__init__.py
renzmc/builtins/utility_functions/__init__.py
renzmc/core/__init__.py
renzmc/core/advanced_types.py
renzmc/core/ast.py
renzmc/core/ast_cache.py
renzmc/core/ast_serializer.py
renzmc/core/base_visitor.py
renzmc/core/error.py
renzmc/core/error_catalog.py
renzmc/core/error_logger.py
renzmc/core/interpreter.py
renzmc/core/lexer.py
renzmc/core/lexer_helpers.py
renzmc/core/parser.py
renzmc/core/parser_type_helpers.py
renzmc/core/rust_integration.py
renzmc/core/token.py
renzmc/core/type_integration.py
renzmc/core/type_system.py
renzmc/core/interpreter/__init__.py
renzmc/core/interpreter/advanced_features.py
renzmc/core/interpreter/base.py
renzmc/core/interpreter/builtin_setup.py
renzmc/core/interpreter/crypto_operations.py
renzmc/core/interpreter/execution_methods.py
renzmc/core/interpreter/file_operations.py
renzmc/core/interpreter/http_operations.py
renzmc/core/interpreter/python_integration.py
renzmc/core/interpreter/renzmc_modules.py
renzmc/core/interpreter/rust_execution.py
renzmc/core/interpreter/scope_management.py
renzmc/core/interpreter/type_system.py
renzmc/core/interpreter/utility.py
renzmc/core/interpreter/methods/__init__.py
renzmc/core/interpreter/methods/advanced_visitors.py
renzmc/core/interpreter/methods/basic_visitors.py
renzmc/core/interpreter/methods/class_visitors.py
renzmc/core/interpreter/methods/control_flow_visitors.py
renzmc/core/interpreter/methods/execution_helpers.py
renzmc/core/interpreter/methods/expression_visitors.py
renzmc/core/interpreter/methods/function_visitors.py
renzmc/core/interpreter/methods/import_visitors.py
renzmc-1.0.0.dist-info/licenses/LICENSE
renzmc-1.0.0.dist-info/METADATA
renzmc-1.0.0.dist-info/WHEEL
renzmc-1.0.0.dist-info/entry_points.txt
renzmc-1.0.0.dist-info/top_level.txt
renzmc-1.0.0.dist-info/RECORD
