Metadata-Version: 2.4
Name: renzmc
Version: 1.0.0
Summary: Bahasa pemrograman berbasis Bahasa Indonesia yang powerful dan modern
Author-email: RenzMc <renzaja11@gmail.com>
Maintainer-email: RenzMc <renzaja11@gmail.com>
License-Expression: MIT
Project-URL: Homepage, https://github.com/RenzMc/RenzmcLang
Project-URL: Documentation, https://github.com/RenzMc/RenzmcLang/tree/main/docs
Project-URL: Repository, https://github.com/RenzMc/RenzmcLang
Project-URL: Bug Tracker, https://github.com/RenzMc/RenzmcLang/issues
Project-URL: Examples, https://github.com/RenzMc/RenzmcLang/tree/main/examples
Keywords: programming-language,indonesian,bahasa-indonesia,interpreter,compiler,education,learning
Classifier: Development Status :: 4 - Beta
Classifier: Intended Audience :: Developers
Classifier: Intended Audience :: Education
Classifier: Intended Audience :: Science/Research
Classifier: Operating System :: OS Independent
Classifier: Programming Language :: Python :: 3
Classifier: Programming Language :: Python :: 3.8
Classifier: Programming Language :: Python :: 3.9
Classifier: Programming Language :: Python :: 3.10
Classifier: Programming Language :: Python :: 3.11
Classifier: Programming Language :: Python :: 3.12
Classifier: Topic :: Software Development :: Interpreters
Classifier: Topic :: Software Development :: Compilers
Classifier: Topic :: Education
Requires-Python: >=3.8
License-File: LICENSE
Requires-Dist: aiohttp>=3.8.1
Requires-Dist: requests>=2.27.1
Requires-Dist: cryptography>=36.0.0
Requires-Dist: python-dateutil>=2.8.2
Requires-Dist: pytz>=2021.3
Requires-Dist: pyyaml>=6.0
Requires-Dist: ujson>=5.1.0
Requires-Dist: regex>=2022.1.18
Provides-Extra: dev
Requires-Dist: pytest>=7.0.0; extra == "dev"
Requires-Dist: pytest-asyncio>=0.18.0; extra == "dev"
Requires-Dist: black>=22.1.0; extra == "dev"
Requires-Dist: isort>=5.10.1; extra == "dev"
Requires-Dist: mypy>=0.931; extra == "dev"
Requires-Dist: flake8>=4.0.1; extra == "dev"
Requires-Dist: pylint; extra == "dev"
Provides-Extra: docs
Requires-Dist: sphinx>=4.0.0; extra == "docs"
Requires-Dist: sphinx-rtd-theme>=1.0.0; extra == "docs"
Provides-Extra: jit
Requires-Dist: numba>=0.55.0; extra == "jit"
Dynamic: license-file
